pymdgilib/__init__.py
pymdgilib/dgi.py
pymdgilib/dgidevice.py
pymdgilib/logfilters.py
pymdgilib/logging.toml
pymdgilib/pydgi_cli.py
pymdgilib/examples/dgi_info.py
pymdgilib/examples/gpio_and_reset_boot_entry.py
pymdgilib/examples/gpio_boot_entry_with_pymcuprog_reset.py
pymdgilib/examples/gpio_in.py
pymdgilib/examples/gpio_out.py
pymdgilib/usblib/__init__.py
pymdgilib/usblib/winkernel32.py
pymdgilib/usblib/winsetupapi.py
pymdgilib/usblib/winusb.py
pymdgilib-0.3.0.3.dist-info/LICENSE.txt
pymdgilib-0.3.0.3.dist-info/METADATA
pymdgilib-0.3.0.3.dist-info/WHEEL
pymdgilib-0.3.0.3.dist-info/entry_points.txt
pymdgilib-0.3.0.3.dist-info/top_level.txt
pymdgilib-0.3.0.3.dist-info/RECORD
