Metadata-Version: 2.1
Name: pymdgilib
Version: 0.3.0.3
Summary: Microchip Data Gateway Interface Tools
Author-email: Microchip Technology <support@microchip.com>
License: MIT
Project-URL: Homepage, https://www.microchip.com
Keywords: Microchip
Classifier: Development Status :: 3 - Alpha
Classifier: Intended Audience :: Developers
Classifier: Topic :: Software Development :: Embedded Systems
Classifier: Programming Language :: Python :: 3
Classifier: Programming Language :: Python :: 3.9
Classifier: Programming Language :: Python :: 3.10
Classifier: Programming Language :: Python :: 3.11
Classifier: Programming Language :: Python :: 3.12
Classifier: Operating System :: Microsoft :: Windows
Classifier: Operating System :: POSIX :: Linux
Classifier: Operating System :: MacOS
Classifier: License :: OSI Approved :: MIT License
Requires-Python: >=3.9
License-File: LICENSE.txt
Requires-Dist: appdirs
Requires-Dist: pyusb
Requires-Dist: tomli>=1.1.0; python_version < "3.11"
Provides-Extra: dev
Requires-Dist: pylint>=2.15; extra == "dev"
Provides-Extra: doc
Requires-Dist: mock; extra == "doc"
Requires-Dist: sphinx; extra == "doc"
Provides-Extra: test
Requires-Dist: mock; extra == "test"
Requires-Dist: pytest; extra == "test"
